Metadata-Version: 2.1
Name: vitality
Version: 0.1.5
Summary: Easily configurable presentation software.
Home-page: https://github.com/brianyu28/vitality
Author: Brian Yu
Author-email: brian@brianyu.me
License: GPL-3.0
Platform: UNKNOWN
